assets/__init__.py
beam_py_visualizer-0.1.0.dist-info/LICENSE
beam_py_visualizer-0.1.0.dist-info/METADATA
beam_py_visualizer-0.1.0.dist-info/WHEEL
beam_py_visualizer-0.1.0.dist-info/entry_points.txt
beam_py_visualizer-0.1.0.dist-info/top_level.txt
beam_py_visualizer-0.1.0.dist-info/RECORD
