Metadata-Version: 2.1
Name: beam_py_visualizer
Version: 0.1.0
Summary: A simple beam stress visualization library for young learners
Home-page: https://github.com/WesternDundrey/beam_py
Author: westerndundrey
Author-email: hijackedpuffin@gmail.com
License: MIT
Classifier: Development Status :: 4 - Beta
Classifier: Intended Audience :: Education
Classifier: Topic :: Education
Classifier: License :: OSI Approved :: MIT License
Classifier: Programming Language :: Python :: 3
Requires-Python: >=3.6
License-File: LICENSE
Requires-Dist: numpy
Requires-Dist: plotly
Requires-Dist: dash
Requires-Dist: dash-bootstrap-components
